[
  {
    "id": 1,
    "title": "Kit Analógico",
    "img": "img/card01.png",
    "recorder": "DVR MOTOROLA DE 4 CANAIS",
    "cameras": "4 CÂMERAS MOTOROLA FULL HD",
    "storage": "HDD DE 1 TB",
    "cable": "CAIXA DE 100 METROS CABO COAXIAL DE 4 MM COM 80% DE MALHA",
    "powerSupply": "FONTE 12 V / 5 A",
    "connectors": "8 CONECTORES BNC E 4 CONECTORES P4"
  },
  {
    "id": 2,
    "title": "Kit IP",
    "img": "img/card01.png",
    "caption": "ACOMPANHA: DVR MOTOROLA 4 CANAIS FULL HD LITE, 4 CÂMERAS MOTOROLA FULL HD, HD 1TB, CABO COAXIAL 4MM 80% 100MT, FONTE 12V 5A, 8 BNC E 4 P4"
  }

]